{
  "generated_at": "2026-05-24T11:41:19",
  "baseline_report_id": 341,
  "baseline_name": "SANDBOX_pool_sentiment_2026-04-27_to_2026-05-22",
  "start_date": "2026-04-27",
  "end_date": "2026-05-22",
  "symbols": [
    "AAPL",
    "AMD",
    "GOOGL",
    "INTC",
    "LLY",
    "MSFT",
    "NVDA",
    "QCOM",
    "QQQ",
    "SPY",
    "TSLA",
    "TXN"
  ],
  "initial_capital": 10000.0,
  "run_count": 36,
  "pm_settings_used": {
    "stop_loss_pct": 0.5,
    "take_profit_pct": 1.25,
    "hold_positions_overnight": false,
    "eod_sell_window_minutes": 5,
    "pending_price_drift_cancel_pct": 0.25,
    "pending_cancel_after_bars": 3,
    "auto_trade_buy_price_offset_pct": 0.01,
    "auto_trade_sell_price_offset_pct": 0.01,
    "sentiment_bucket_persistence": 5,
    "market_sentiment_strategies": {
      "crash": "rsi",
      "bearish": "macd",
      "neutral": "bollinger_bands",
      "bullish": "sma_crossover",
      "euphoric": "rsi"
    }
  }
}
